MANIFEST.in
README.rst
setup.py
adi/__init__.py
adi.enabletopics.egg-info/PKG-INFO
adi.enabletopics.egg-info/SOURCES.txt
adi.enabletopics.egg-info/dependency_links.txt
adi.enabletopics.egg-info/entry_points.txt
adi.enabletopics.egg-info/namespace_packages.txt
adi.enabletopics.egg-info/not-zip-safe
adi.enabletopics.egg-info/requires.txt
adi.enabletopics.egg-info/top_level.txt
adi/enabletopics/__init__.py
adi/enabletopics/configure.zcml
adi/enabletopics/profiles/default/controlpanel.xml
adi/enabletopics/profiles/default/metadata.xml
adi/enabletopics/profiles/default/types/Topic.xml
docs/CHANGES.rst