Metadata-Version: 1.1
Name: adi.enabletopics
Version: 0.1
Summary: Plone add-on to re-enable old-style-collections 'Topic' disabled by default since of Plone 4.1
Home-page: https://github.com/ida/adi.enabletopics/
Author: Ida Ebkes
Author-email: contact@ida-ebkes.eu
License: GPL
Platform: UNKNOWN
Classifier: Framework :: Plone
Classifier: Programming Language :: Python
